quantylab/rest_api_client.py
quantylab_client-1.0.7.dist-info/METADATA
quantylab_client-1.0.7.dist-info/WHEEL
quantylab_client-1.0.7.dist-info/top_level.txt
quantylab_client-1.0.7.dist-info/RECORD
