Metadata-Version: 2.4
Name: quantylab-client
Version: 1.0.7
Author-email: Quantylab <quantylab@gmail.com>
License: MIT
Project-URL: Homepage, https://github.com/quantylab/quantylab-client
Keywords: quant,trading,research
Requires-Python: >=3.12
Requires-Dist: requests
